arlynupscale/__init__.py
arlynupscale/driver.py
arlynupscale/py.typed
arlynupscale/util.py
arlynupscale-0.0.6.dist-info/LICENSE.txt
arlynupscale-0.0.6.dist-info/METADATA
arlynupscale-0.0.6.dist-info/WHEEL
arlynupscale-0.0.6.dist-info/top_level.txt
arlynupscale-0.0.6.dist-info/RECORD
